CONTRIBUTING.rst
LICENSE.txt
MANIFEST.in
README.rst
requirements-aiohttp.txt
requirements-devel.txt
setup.cfg
setup.py
connexion/__init__.py
connexion/__main__.py
connexion/cli.py
connexion/exceptions.py
connexion/handlers.py
connexion/lifecycle.py
connexion/mock.py
connexion/operation.py
connexion/options.py
connexion/problem.py
connexion/resolver.py
connexion/utils.py
connexion/apis/__init__.py
connexion/apis/abstract.py
connexion/apis/aiohttp_api.py
connexion/apis/flask_api.py
connexion/apis/flask_utils.py
connexion/apps/__init__.py
connexion/apps/abstract.py
connexion/apps/aiohttp_app.py
connexion/apps/flask_app.py
connexion/decorators/__init__.py
connexion/decorators/coroutine_wrappers.py
connexion/decorators/decorator.py
connexion/decorators/metrics.py
connexion/decorators/parameter.py
connexion/decorators/produces.py
connexion/decorators/response.py
connexion/decorators/security.py
connexion/decorators/validation.py
connexion/vendor/swagger-ui/index.html
connexion/vendor/swagger-ui/index.html.patch
connexion/vendor/swagger-ui/o2c.html
connexion/vendor/swagger-ui/swagger-ui.js
connexion/vendor/swagger-ui/swagger-ui.min.js
connexion/vendor/swagger-ui/update.sh
connexion/vendor/swagger-ui/css/print.css
connexion/vendor/swagger-ui/css/reset.css
connexion/vendor/swagger-ui/css/screen.css
connexion/vendor/swagger-ui/css/style.css
connexion/vendor/swagger-ui/css/typography.css
connexion/vendor/swagger-ui/fonts/DroidSans-Bold.ttf
connexion/vendor/swagger-ui/fonts/DroidSans.ttf
connexion/vendor/swagger-ui/images/collapse.gif
connexion/vendor/swagger-ui/images/expand.gif
connexion/vendor/swagger-ui/images/explorer_icons.png
connexion/vendor/swagger-ui/images/favicon-16x16.png
connexion/vendor/swagger-ui/images/favicon-32x32.png
connexion/vendor/swagger-ui/images/favicon.ico
connexion/vendor/swagger-ui/images/logo_small.png
connexion/vendor/swagger-ui/images/pet_store_api.png
connexion/vendor/swagger-ui/images/throbber.gif
connexion_aiohttp.egg-info/PKG-INFO
connexion_aiohttp.egg-info/SOURCES.txt
connexion_aiohttp.egg-info/dependency_links.txt
connexion_aiohttp.egg-info/entry_points.txt
connexion_aiohttp.egg-info/requires.txt
connexion_aiohttp.egg-info/top_level.txt