Metadata-Version: 2.1
Name: connexion-aiohttp
Version: 1.5
Summary: Connexion - API first applications with OpenAPI/Swagger and Flask
Home-page: https://github.com/zalando/connexion
Author: Zalando SE
License: Apache License Version 2.0
Keywords: openapi oai swagger rest api oauth flask microservice framework
Platform: UNKNOWN
Classifier: Programming Language :: Python
Classifier: Programming Language :: Python :: 2.7
Classifier: Programming Language :: Python :: 3.4
Classifier: Programming Language :: Python :: 3.5
Classifier: Programming Language :: Python :: 3.6
Classifier: Development Status :: 5 - Production/Stable
Classifier: Intended Audience :: Developers
Classifier: Operating System :: OS Independent
Classifier: Topic :: Internet :: WWW/HTTP :: WSGI :: Application
Classifier: Topic :: Software Development :: Libraries :: Application Frameworks
Provides-Extra: tests
Provides-Extra: flask
Provides-Extra: aiohttp
Provides-Extra: ujson
